{"cameraMode":{"drawMode":0,"name":"Shaded","section":"Shading Mode"},"sceneLighting":false,"audioPlay":false,"sceneViewState":{"m_AlwaysRefresh":false,"showFog":true,"showSkybox":false,"showFlares":true,"showImageEffects":true,"showParticleSystems":true,"showVisualEffectGraphs":true,"m_FxEnabled":true},"in2DMode":false,"pivot":{"x":0.0,"y":-0.00000286102294921875,"z":0.0},"rotation":{"x":0.05741245299577713,"y":0.8985507488250732,"z":-0.12372983247041702,"w":0.4175378680229187},"size":8.022920608520508,"orthographic":false}