{"cameraMode":{"drawMode":0,"name":"Shaded","section":"Shading Mode"},"sceneLighting":false,"audioPlay":false,"sceneViewState":{"m_AlwaysRefresh":false,"showFog":true,"showSkybox":false,"showFlares":true,"showImageEffects":true,"showParticleSystems":true,"showVisualEffectGraphs":true,"m_FxEnabled":true},"in2DMode":false,"pivot":{"x":252.26463317871095,"y":33.473514556884769,"z":107.54557037353516},"rotation":{"x":-0.37818971276283266,"y":-0.10213188827037811,"z":0.0422070175409317,"w":-0.9193012118339539},"size":7.279641151428223,"orthographic":false}